{
  "last_action": "mage",
  "buttons": [
    {
      "x": 115,
      "y": 138,
      "trigger": 1771433722432
    },
    {
      "x": 115,
      "y": 168,
      "trigger": 1771367226781
    },
    {
      "x": 115,
      "y": 226,
      "trigger": 1771368998203
    },
    {
      "x": 115,
      "y": 275,
      "trigger": 1771432139978
    },
    {
      "x": 115,
      "y": 325,
      "trigger": 1771366543804
    },
    {
      "x": 115,
      "y": 376,
      "trigger": 1771431422499
    },
    {
      "x": 115,
      "y": 433,
      "trigger": 1771365272479
    },
    {
      "x": 115,
      "y": 484,
      "trigger": 1771088360894
    }
  ]
}